SocketWrapper/Client.py
SocketWrapper/Server.py
SocketWrapper/__init__.py
SocketWrapper-0.2.3.dist-info/LICENSE
SocketWrapper-0.2.3.dist-info/METADATA
SocketWrapper-0.2.3.dist-info/WHEEL
SocketWrapper-0.2.3.dist-info/top_level.txt
SocketWrapper-0.2.3.dist-info/RECORD
